iflow_mcp_nickzren_opentargets_mcp-0.4.0.dist-info/licenses/LICENSE
opentargets_mcp/__init__.py
opentargets_mcp/exceptions.py
opentargets_mcp/queries.py
opentargets_mcp/resolver.py
opentargets_mcp/server.py
opentargets_mcp/utils.py
opentargets_mcp/tools/__init__.py
opentargets_mcp/tools/disease.py
opentargets_mcp/tools/evidence.py
opentargets_mcp/tools/graphql.py
opentargets_mcp/tools/meta.py
opentargets_mcp/tools/search.py
opentargets_mcp/tools/study.py
opentargets_mcp/tools/variant.py
opentargets_mcp/tools/drug/__init__.py
opentargets_mcp/tools/drug/associations.py
opentargets_mcp/tools/drug/identity.py
opentargets_mcp/tools/drug/safety.py
opentargets_mcp/tools/target/__init__.py
opentargets_mcp/tools/target/associations.py
opentargets_mcp/tools/target/biology.py
opentargets_mcp/tools/target/identity.py
opentargets_mcp/tools/target/safety.py
iflow_mcp_nickzren_opentargets_mcp-0.4.0.dist-info/METADATA
iflow_mcp_nickzren_opentargets_mcp-0.4.0.dist-info/WHEEL
iflow_mcp_nickzren_opentargets_mcp-0.4.0.dist-info/entry_points.txt
iflow_mcp_nickzren_opentargets_mcp-0.4.0.dist-info/top_level.txt
iflow_mcp_nickzren_opentargets_mcp-0.4.0.dist-info/RECORD
