Metadata-Version: 2.4
Name: iflow-mcp_nickzren_opentargets-mcp
Version: 0.4.0
Summary: MCP server for Open Targets Platform biomedical data access
Author: Nick Ren
License: MIT
Project-URL: Homepage, https://github.com/nickzren/opentargets-mcp
Project-URL: Repository, https://github.com/nickzren/opentargets-mcp
Project-URL: Documentation, https://github.com/nickzren/opentargets-mcp#readme
Keywords: mcp,open-targets,biomedical,drug-discovery,genetics
Classifier: Development Status :: 4 - Beta
Classifier: Intended Audience :: Science/Research
Classifier: License :: OSI Approved :: MIT License
Classifier: Programming Language :: Python :: 3
Classifier: Programming Language :: Python :: 3.12
Classifier: Topic :: Scientific/Engineering :: Bio-Informatics
Classifier: Topic :: Scientific/Engineering :: Medical Science Apps.
Requires-Python: >=3.11
License-File: LICENSE
Requires-Dist: fastmcp>=2.0.0
Requires-Dist: aiohttp
Requires-Dist: graphql-core>=3.2
Requires-Dist: python-dotenv
Provides-Extra: dev
Requires-Dist: mcp; extra == "dev"
Requires-Dist: pytest; extra == "dev"
Requires-Dist: pytest-asyncio; extra == "dev"
Requires-Dist: thefuzz; extra == "dev"
Requires-Dist: black; extra == "dev"
Requires-Dist: ruff; extra == "dev"
Provides-Extra: examples
Requires-Dist: openai; extra == "examples"
Requires-Dist: thefuzz; extra == "examples"
Dynamic: license-file
